{"inkVersion":21,"root":[["#","^using SetPortrait","/#","#","^using HasItem","/#","#","^using PlayCutscene","/#","#","^using GetVar","/#","#","^using SetVar","/#",["ev","str","^elevator","/str",{"x()":"GetVar","exArgs":1},-1,"==","/ev",{"->":".^.b","c":true},{"b":["\n",{"->":"FirstInteraction"},{"->":"0.18"},null]}],["ev","str","^ElevatorKey","/str",{"x()":"HasItem","exArgs":1},"/ev",{"->":".^.b","c":true},{"b":["\n",{"->":"UseElevator"},{"->":"0.18"},null]}],[{"->":".^.b"},{"b":["\n",{"->":"SecondEncounter"},{"->":"0.18"},null]}],"nop","\n",["done",{"#f":5,"#n":"g-0"}],null],"done",{"FirstInteraction":["ev","str","^elevator","/str",1,{"x()":"SetVar","exArgs":2},"pop","/ev","\n","ev","str","^Alice","/str",{"x()":"SetPortrait","exArgs":1},"pop","/ev","\n","^Patrz winda!","\n","^Z jej pomocą powinniśmy dostać się do głębin raz dwa","\n","^!","\n","^Nie działa!","\n","ev","str","^Fex","/str",{"x()":"SetPortrait","exArgs":1},"pop","/ev","\n","^Zdaje mi się że wymaga jakiegoś klucza do uruchomienia","\n","ev","str","^ElevatorKey","/str",{"x()":"HasItem","exArgs":1},"/ev",[{"->":".^.b","c":true},{"b":["\n","^O! Ten który znaleźliśmy wcześniej pasuje","\n",{"->":"UseElevator"},{"->":".^.^.^.43"},null]}],[{"->":".^.b"},{"b":["\n","^Rozglądnijmy się za nim","\n",{"->":".^.^.^.43"},null]}],"nop","\n","end",{"#f":1}],"SecondEncounter":["^Winda","\n","^Wymaga klucza do uruchomienia","\n","end",{"#f":1}],"UseElevator":[["ev","str","^","/str",{"x()":"SetPortrait","exArgs":1},"pop","/ev","\n","^Czy chcesz skorzystać z windy?","\n","ev","str","^Tak","/str","/ev",{"*":".^.c-0","flg":20},"ev","str","^Nie","/str","/ev",{"*":".^.c-1","flg":20},{"c-0":["\n","ev","str","^Elevator1","/str",{"x()":"PlayCutscene","exArgs":1},"pop","/ev","\n","end",{"#f":5}],"c-1":["\n","end",{"#f":5}]}],{"#f":1}],"#f":1}],"listDefs":{}}